clover/__init__.py
clover/generators/__init__.py
clover/generators/base.py
clover/generators/ctabgan_generator.py
clover/generators/ctgan_generator.py
clover/generators/dataSynthesizer.py
clover/generators/findiff_generator.py
clover/generators/mst_generator.py
clover/generators/smote.py
clover/generators/synthpop_generator.py
clover/generators/tvae_generator.py
clover/generators/external/__init__.py
clover/generators/external/ctabgan/LICENSE
clover/generators/external/ctabgan/README.md
clover/generators/external/ctabgan/__init__.py
clover/generators/external/ctabgan/ctabgan_synthesizer.py
clover/generators/external/ctabgan/data_preparation.py
clover/generators/external/ctabgan/model/__init__.py
clover/generators/external/ctabgan/model/synthesizer/__init__.py
clover/generators/external/ctabgan/model/synthesizer/transformer.py
clover/generators/external/ctgan/__init__.py
clover/generators/external/ctgan/data_transformer.py
clover/generators/external/ctgan/single_table/LICENSE
clover/generators/external/ctgan/single_table/__init__.py
clover/generators/external/ctgan/single_table/dp_ctgan.py
clover/generators/external/ctgan/synthesizers/LICENSE
clover/generators/external/ctgan/synthesizers/__init__.py
clover/generators/external/ctgan/synthesizers/ctgan.py
clover/generators/external/ctgan/synthesizers/tvae.py
clover/generators/external/dpart/LICENSE
clover/generators/external/dpart/README.md
clover/generators/external/dpart/__init__.py
clover/generators/external/dpart/dpart/__init__.py
clover/generators/external/dpart/dpart/dpart.py
clover/generators/external/dpart/dpart/engines/__init__.py
clover/generators/external/dpart/dpart/engines/dp_synthpop.py
clover/generators/external/dpart/dpart/engines/independent.py
clover/generators/external/dpart/dpart/engines/priv_bayes.py
clover/generators/external/dpart/dpart/methods/__init__.py
clover/generators/external/dpart/dpart/methods/decision_tree_classifier.py
clover_synth-0.1.0.dist-info/METADATA
clover_synth-0.1.0.dist-info/WHEEL
clover_synth-0.1.0.dist-info/RECORD
