Metadata-Version: 2.4
Name: clover-synth
Version: 0.1.0
Summary: Clover: Synthetic Health Data Generation and Validation Library
Author: Katleen Blanchet
Author-email: Yue Qi <yue.qi.chum@ssss.gouv.qc.ca>, Lorrie Herbault <lorrie.herbault.chum@ssss.gouv.qc.ca>
Maintainer-email: Yue Qi <yue.qi.chum@ssss.gouv.qc.ca>, Lorrie Herbault <lorrie.herbault.chum@ssss.gouv.qc.ca>
License: Apache License (2.0)
Keywords: data privacy,healthcare data,synthetic data
Requires-Python: <3.11,>=3.8
Requires-Dist: category-encoders<3.0,>=2.6.1
Requires-Dist: datasynthesizer<0.2.0,>=0.1.11
Requires-Dist: diffprivlib<0.7,>=0.6.4
Requires-Dist: disjoint-set<1.0,>=0.7.4
Requires-Dist: imbalanced-learn<0.13.0,>=0.11.0
Requires-Dist: jinja2<=4.0
Requires-Dist: matplotlib<4.0,>=3.7.1
Requires-Dist: networkx<4.0,>=3.1
Requires-Dist: numpy<2.0,==1.23.5
Requires-Dist: opacus<1.5.0,==1.4.0
Requires-Dist: optuna<4.1.1,>=3.2.0
Requires-Dist: pandas<2.2.3,>=1.5.3
Requires-Dist: pymoo<0.7,==0.6.0.1
Requires-Dist: pytest<8.0
Requires-Dist: ray[tune]<3.0,>=2.5.1
Requires-Dist: scikit-learn<1.5.3,>=1.4
Requires-Dist: scipy<4.66.6,>=1.10.1
Requires-Dist: sdv<1.3.0,>=1.2.1
Requires-Dist: seaborn<1.0,==0.13.2
Requires-Dist: tqdm<5.0,==4.65.0
Requires-Dist: xgboost<2.1.3,>=1.7.5
Provides-Extra: dev
Requires-Dist: black==25.1.0; extra == 'dev'
Requires-Dist: black[jupyter]; extra == 'dev'
Requires-Dist: furo==2023.9.10; extra == 'dev'
Requires-Dist: icecream==2.1.3; extra == 'dev'
Requires-Dist: ipython==8.12.3; extra == 'dev'
Requires-Dist: nbsphinx-link==1.3.0; extra == 'dev'
Requires-Dist: nbsphinx==0.9.1; extra == 'dev'
Requires-Dist: pandoc==2.3; extra == 'dev'
Requires-Dist: pytest==7.3.1; extra == 'dev'
Requires-Dist: sphinx-autodoc-typehints==1.23.0; extra == 'dev'
Requires-Dist: sphinx==6.2.1; extra == 'dev'
Requires-Dist: tomli-w==1.0.0; extra == 'dev'
Requires-Dist: tomli==2.0.1; extra == 'dev'
